rhclient/__init__.py
rhclient/pythonClient.py
rhclient-1.2.1.dist-info/METADATA
rhclient-1.2.1.dist-info/WHEEL
rhclient-1.2.1.dist-info/top_level.txt
rhclient-1.2.1.dist-info/RECORD
