Metadata-Version: 2.1
Name: rhclient
Version: 1.2.1
Summary: Python REST Service Test utility
Home-page: https://www.restharness.com
Author: Robbie Reed
Author-email: robbiereed@psg-inc.net
License: UNKNOWN
Platform: UNKNOWN
Requires-Python: >=3.6
Requires-Dist: requests
